dolphindb_mcp_server/.server.py.swp
dolphindb_mcp_server/__init__.py
dolphindb_mcp_server/ddb.py
dolphindb_mcp_server/server.py
dolphindb_mcp_server-0.1.0.dist-info/METADATA
dolphindb_mcp_server-0.1.0.dist-info/WHEEL
dolphindb_mcp_server-0.1.0.dist-info/entry_points.txt
dolphindb_mcp_server-0.1.0.dist-info/RECORD
