Metadata-Version: 2.4
Name: dolphindb-mcp-server
Version: 0.1.0
Summary: dolphindb mcp server
Requires-Python: >=3.12
Requires-Dist: dolphindb
Requires-Dist: fastapi[standard]
Requires-Dist: fastmcp
Requires-Dist: httpx>=0.28.1
Requires-Dist: mcp>=1.1.2
